{
  "indices": {
    "error": "allIndices API returned None",
    "time": "2026-03-16T07:05:50.085915+00:00"
  },
  "oc_NIFTY": {
    "error": "API returned None",
    "time": "2026-03-16T07:05:53.421865+00:00"
  },
  "oc_BANKNIFTY": {
    "error": "API returned None",
    "time": "2026-03-16T07:05:57.744143+00:00"
  },
  "oc_FINNIFTY": {
    "error": "API returned None",
    "time": "2026-03-16T07:06:02.074458+00:00"
  },
  "fii_dii": {
    "error": "All FII endpoints returned None",
    "time": "2026-03-16T07:06:55.322516+00:00"
  }
}